{"data":{"propertyOrder":{},"properties":{"id":{"name":"id","reference":"scalar","primary":true,"type":"uuid","array":false},"name":{"name":"name","reference":"scalar","getter":false,"setter":false,"type":"string","array":false},"permissions":{"name":"permissions","type":"Permissions","reference":"embedded","object":true,"prefix":true,"array":true}},"props":[{"name":"id","reference":"scalar","primary":true,"type":"uuid","array":false},{"name":"name","reference":"scalar","getter":false,"setter":false,"type":"string","array":false},{"name":"permissions","type":"Permissions","reference":"embedded","object":true,"prefix":true,"array":true}],"primaryKeys":["id"],"filters":{},"hooks":{},"indexes":[],"uniques":[],"checks":[],"concurrencyCheckKeys":{},"className":"Role","path":"./dist/roles/entities/role.entity.js","name":"Role","abstract":false,"constructorParams":[],"toJsonParams":[],"useCache":true,"compositePK":false,"relations":[],"collection":"role"},"origin":"./dist/roles/entities/role.entity.js","hash":"438e50e25cea6db16fb8b4546f7db4ad","version":"5.6.8"}
